surficial/__init__.py
surficial/cli/__init__.py
surficial/cli/buffer.py
surficial/cli/defaults.py
surficial/cli/network.py
surficial/cli/plan.py
surficial/cli/profile.py
surficial/cli/repair.py
surficial/cli/station.py
surficial/cli/surficial.py
surficial/cli/util.py
surficial/core/__init__.py
surficial/core/alignment.py
surficial/core/api.py
surficial/ops/__init__.py
surficial/ops/graph.py
surficial/ops/shape.py
surficial-0.0.2.dist-info/DESCRIPTION.rst
surficial-0.0.2.dist-info/METADATA
surficial-0.0.2.dist-info/RECORD
surficial-0.0.2.dist-info/SOURCES.sync-conflict-20160812-140528.txt
surficial-0.0.2.dist-info/WHEEL
surficial-0.0.2.dist-info/entry_points.sync-conflict-20160812-140510.txt
surficial-0.0.2.dist-info/entry_points.txt
surficial-0.0.2.dist-info/metadata.json
surficial-0.0.2.dist-info/top_level.txt
