Metadata-Version: 2.0
Name: surficial
Version: 0.0.2
Summary: Python library and CLI tools to support analysis of stream long-profiles
Home-page: http://github.com/mrahnis/surficial
Author: Michael Rahnis
Author-email: michael.rahnis@fandm.edu
License: BSD
Keywords: cross-section,topography,survey,plotting
Platform: UNKNOWN
Classifier: Development Status :: 3 - Alpha
Classifier: License :: OSI Approved :: BSD License
Classifier: Programming Language :: Python
Classifier: Programming Language :: Python :: 3
Classifier: Topic :: Scientific/Engineering :: GIS
Requires-Dist: click
Requires-Dist: descartes
Requires-Dist: drapery
Requires-Dist: fiona
Requires-Dist: matplotlib
Requires-Dist: networkx
Requires-Dist: pandas
Requires-Dist: rasterio
Requires-Dist: shapely
